auth_sdk/__init__.py
auth_sdk/auth_service.py
auth_sdk/auth_types.py
arvasit_auth_sdk-0.2.3.dist-info/METADATA
arvasit_auth_sdk-0.2.3.dist-info/WHEEL
arvasit_auth_sdk-0.2.3.dist-info/top_level.txt
arvasit_auth_sdk-0.2.3.dist-info/RECORD
