Metadata-Version: 2.4
Name: arvasit-auth-sdk
Version: 0.2.3
Summary: A comprehensive authentication SDK for Python with Pydantic support. Features include user registration, login, 2FA, password management, and secure token handling.
Author: pratik
License-Expression: MIT
Project-URL: Homepage, https://github.com/arvasit/auth-sdk
Project-URL: Bug Tracker, https://github.com/arvasit/auth-sdk/issues
Keywords: auth,sdk,arvasit,authentication,2fa,two-factor,login,signup,python,pydantic,jwt,oauth,security,password,verification
Classifier: Development Status :: 4 - Beta
Classifier: Intended Audience :: Developers
Classifier: Programming Language :: Python :: 3
Classifier: Programming Language :: Python :: 3.8
Classifier: Programming Language :: Python :: 3.9
Classifier: Programming Language :: Python :: 3.10
Classifier: Programming Language :: Python :: 3.11
Classifier: Programming Language :: Python :: 3.12
Classifier: Topic :: Software Development :: Libraries :: Python Modules
Classifier: Topic :: Security
Classifier: Topic :: Internet :: WWW/HTTP :: Dynamic Content
Requires-Python: >=3.8
Requires-Dist: requests>=2.31.0
Requires-Dist: python-dateutil>=2.8.2
Requires-Dist: pydantic>=2.0.0
